todero/__init__.py
todero/cli.py
todero-0.0.2.data/scripts/todero
todero-0.0.2.dist-info/METADATA
todero-0.0.2.dist-info/WHEEL
todero-0.0.2.dist-info/top_level.txt
todero-0.0.2.dist-info/RECORD
